pyawsopstoolkit/exceptions/__init__.py
pyawsopstoolkit/exceptions/__main__.py
pyawsopstoolkit/exceptions/__validations__.py
pyawsopstoolkit.exceptions-0.1.2.dist-info/LICENSE
pyawsopstoolkit.exceptions-0.1.2.dist-info/METADATA
pyawsopstoolkit.exceptions-0.1.2.dist-info/WHEEL
pyawsopstoolkit.exceptions-0.1.2.dist-info/top_level.txt
pyawsopstoolkit.exceptions-0.1.2.dist-info/RECORD
