Metadata-Version: 2.1
Name: pyawsopstoolkit.exceptions
Version: 0.1.2
Summary: This package offers a collection of exception classes tailored for handling errors within the AWS Ops Toolkit.
Home-page: https://github.com/coldsofttech/pyawsopstoolkit.exceptions
Author: coldsofttech
License: MIT
Keywords: aws,toolkit,exceptions,amazon-web-services,awsopstoolkit,aws-ops-toolkit
Classifier: Development Status :: 4 - Beta
Classifier: Intended Audience :: Developers
Classifier: Topic :: Software Development :: Libraries
Classifier: Topic :: Software Development :: Libraries :: Python Modules
Classifier: License :: OSI Approved :: MIT License
Classifier: Programming Language :: Python :: 3.10
Classifier: Programming Language :: Python :: 3.11
Classifier: Programming Language :: Python :: 3.12
License-File: LICENSE
